flatnet/__init__.py
flatnet/train.py
flatnet/modules/__init__.py
flatnet/modules/flatnet_nn.py
flatnet-0.2.1.dist-info/METADATA
flatnet-0.2.1.dist-info/WHEEL
flatnet-0.2.1.dist-info/top_level.txt
flatnet-0.2.1.dist-info/RECORD
